gaiaos.py
helper/__init__.py
napalm_gaiaos/__init__.py
napalm_gaiaos/gaiaos.py
napalm_gaiaos/helper/__init__.py
napalm_gaia-0.0.15.dist-info/LICENSE
napalm_gaia-0.0.15.dist-info/METADATA
napalm_gaia-0.0.15.dist-info/WHEEL
napalm_gaia-0.0.15.dist-info/top_level.txt
napalm_gaia-0.0.15.dist-info/RECORD
