Metadata-Version: 2.1
Name: napalm-gaia
Version: 0.0.15
Summary: napalm driver plugin for checkpoint gaia-os
Home-page: https://github.com/remingu/napalm-gaia
Author: Daniel Schlifka(remingu), Pavel Smejkal(mbtathcx>
Author-email: Daniel Schlifka <remingu@techturn.de>, Pavel Smejkal <sm3jkal@centrum.cz
License: Apache 2.0
Project-URL: Bug Reports, https://github.com/remingu/napalm-gaia/issues
Project-URL: Source, https://github.com/remingu/napalm-gaia
Keywords: development napalm checkpoint gaia
Platform: UNKNOWN
Requires-Python: >=3.6
Requires-Dist: napalm (==2.5.0)
